{
    "version": "2023-07-14 06:55:02",
    "imagePath": "Basler_acA4112-20uc__40059801__20201013_123550334_321_right.jpg",
    "imageHeight": 3000,
    "imageWidth": 2048,
    "shapes": [
        {
            "label": "2-1",
            "points": [
                [
                    3172.3214285714284,
                    721.8749999999999
                ]
            ],
            "group_id": 56,
            "shape_type": "point",
            "flags": {}
        },
        {
            "label": "2-2",
            "points": [
                [
                    3149.1071428571427,
                    727.6785714285713
                ]
            ],
            "group_id": 56,
            "shape_type": "point",
            "flags": {}
        },
        {
            "label": "2-1",
            "points": [
                [
                    3244.1964285714284,
                    744.6428571428571
                ]
            ],
            "group_id": 57,
            "shape_type": "point",
            "flags": {}
        },
        {
            "label": "2-2",
            "points": [
                [
                    3254.017857142857,
                    775.8928571428571
                ]
            ],
            "group_id": 57,
            "shape_type": "point",
            "flags": {}
        },
        {
            "label": "3-1",
            "points": [
                [
                    3272.3214285714284,
                    748.2142857142857
                ]
            ],
            "group_id": 58,
            "shape_type": "point",
            "flags": {}
        },
        {
            "label": "3-2",
            "points": [
                [
                    3276.3392857142853,
                    774.1071428571428
                ]
            ],
            "group_id": 58,
            "shape_type": "point",
            "flags": {}
        },
        {
            "label": "3-3",
            "points": [
                [
                    3266.9642857142853,
                    803.1249999999999
                ]
            ],
            "group_id": 58,
            "shape_type": "point",
            "flags": {}
        },
        {
            "label": "3-1",
            "points": [
                [
                    3213.793103448276,
                    809.6551724137931
                ]
            ],
            "group_id": 59,
            "shape_type": "point",
            "flags": {}
        },
        {
            "label": "3-2",
            "points": [
                [
                    3207.5862068965516,
                    870.344827586207
                ]
            ],
            "group_id": 59,
            "shape_type": "point",
            "flags": {}
        },
        {
            "label": "3-3",
            "points": [
                [
                    3222.0689655172414,
                    897.9310344827586
                ]
            ],
            "group_id": 59,
            "shape_type": "point",
            "flags": {}
        },
        {
            "label": "4-1",
            "points": [
                [
                    3248.9655172413795,
                    807.5862068965517
                ]
            ],
            "group_id": 60,
            "shape_type": "point",
            "flags": {}
        },
        {
            "label": "4-2",
            "points": [
                [
                    3248.9655172413795,
                    839.3103448275863
                ]
            ],
            "group_id": 60,
            "shape_type": "point",
            "flags": {}
        },
        {
            "label": "4-3",
            "points": [
                [
                    3252.4137931034484,
                    872.4137931034483
                ]
            ],
            "group_id": 60,
            "shape_type": "point",
            "flags": {}
        },
        {
            "label": "4-4",
            "points": [
                [
                    3249.655172413793,
                    899.3103448275863
                ]
            ],
            "group_id": 60,
            "shape_type": "point",
            "flags": {}
        },
        {
            "label": "3-1",
            "points": [
                [
                    3230.344827586207,
                    926.2068965517242
                ]
            ],
            "group_id": 61,
            "shape_type": "point",
            "flags": {}
        },
        {
            "label": "3-2",
            "points": [
                [
                    3203.448275862069,
                    936.551724137931
                ]
            ],
            "group_id": 61,
            "shape_type": "point",
            "flags": {}
        },
        {
            "label": "3-3",
            "points": [
                [
                    3177.241379310345,
                    933.7931034482759
                ]
            ],
            "group_id": 61,
            "shape_type": "point",
            "flags": {}
        },
        {
            "label": "2-1",
            "points": [
                [
                    3143.448275862069,
                    957.2413793103449
                ]
            ],
            "group_id": 62,
            "shape_type": "point",
            "flags": {}
        },
        {
            "label": "2-2",
            "points": [
                [
                    3139.3103448275865,
                    985.5172413793103
                ]
            ],
            "group_id": 62,
            "shape_type": "point",
            "flags": {}
        },
        {
            "label": "3-1",
            "points": [
                [
                    3202.7586206896553,
                    966.2068965517242
                ]
            ],
            "group_id": 63,
            "shape_type": "point",
            "flags": {}
        },
        {
            "label": "3-2",
            "points": [
                [
                    3204.137931034483,
                    993.7931034482759
                ]
            ],
            "group_id": 63,
            "shape_type": "point",
            "flags": {}
        },
        {
            "label": "3-3",
            "points": [
                [
                    3209.655172413793,
                    1024.1379310344828
                ]
            ],
            "group_id": 63,
            "shape_type": "point",
            "flags": {}
        },
        {
            "label": "4-1",
            "points": [
                [
                    3234.4827586206898,
                    968.2758620689656
                ]
            ],
            "group_id": 64,
            "shape_type": "point",
            "flags": {}
        },
        {
            "label": "4-2",
            "points": [
                [
                    3241.379310344828,
                    1001.3793103448277
                ]
            ],
            "group_id": 64,
            "shape_type": "point",
            "flags": {}
        },
        {
            "label": "4-3",
            "points": [
                [
                    3241.379310344828,
                    1033.7931034482758
                ]
            ],
            "group_id": 64,
            "shape_type": "point",
            "flags": {}
        },
        {
            "label": "4-4",
            "points": [
                [
                    3217.9310344827586,
                    1068.9655172413793
                ]
            ],
            "group_id": 64,
            "shape_type": "point",
            "flags": {}
        },
        {
            "label": "3-1",
            "points": [
                [
                    3191.034482758621,
                    960.6896551724138
                ]
            ],
            "group_id": 65,
            "shape_type": "point",
            "flags": {}
        },
        {
            "label": "3-2",
            "points": [
                [
                    3186.896551724138,
                    974.4827586206897
                ]
            ],
            "group_id": 65,
            "shape_type": "point",
            "flags": {}
        },
        {
            "label": "3-3",
            "points": [
                [
                    3180.0,
                    988.2758620689656
                ]
            ],
            "group_id": 65,
            "shape_type": "point",
            "flags": {}
        },
        {
            "label": "4-1",
            "points": [
                [
                    3152.4137931034484,
                    960.0
                ]
            ],
            "group_id": 66,
            "shape_type": "point",
            "flags": {}
        },
        {
            "label": "4-2",
            "points": [
                [
                    3150.344827586207,
                    994.4827586206897
                ]
            ],
            "group_id": 66,
            "shape_type": "point",
            "flags": {}
        },
        {
            "label": "4-3",
            "points": [
                [
                    3137.9310344827586,
                    1018.6206896551724
                ]
            ],
            "group_id": 66,
            "shape_type": "point",
            "flags": {}
        },
        {
            "label": "4-4",
            "points": [
                [
                    3127.5862068965516,
                    1046.2068965517242
                ]
            ],
            "group_id": 66,
            "shape_type": "point",
            "flags": {}
        },
        {
            "label": "3-1",
            "points": [
                [
                    3166.896551724138,
                    962.0689655172414
                ]
            ],
            "group_id": 67,
            "shape_type": "point",
            "flags": {}
        },
        {
            "label": "3-2",
            "points": [
                [
                    3164.8275862068967,
                    990.344827586207
                ]
            ],
            "group_id": 67,
            "shape_type": "point",
            "flags": {}
        },
        {
            "label": "3-3",
            "points": [
                [
                    3164.137931034483,
                    1020.0
                ]
            ],
            "group_id": 67,
            "shape_type": "point",
            "flags": {}
        },
        {
            "label": "3-1",
            "points": [
                [
                    3212.4137931034484,
                    1134.4827586206898
                ]
            ],
            "group_id": 68,
            "shape_type": "point",
            "flags": {}
        },
        {
            "label": "3-2",
            "points": [
                [
                    3232.4137931034484,
                    1158.6206896551726
                ]
            ],
            "group_id": 68,
            "shape_type": "point",
            "flags": {}
        },
        {
            "label": "3-3",
            "points": [
                [
                    3248.2758620689656,
                    1184.8275862068965
                ]
            ],
            "group_id": 68,
            "shape_type": "point",
            "flags": {}
        },
        {
            "label": "3-1",
            "points": [
                [
                    3157.9310344827586,
                    1142.7586206896551
                ]
            ],
            "group_id": 69,
            "shape_type": "point",
            "flags": {}
        },
        {
            "label": "3-2",
            "points": [
                [
                    3146.206896551724,
                    1168.2758620689656
                ]
            ],
            "group_id": 69,
            "shape_type": "point",
            "flags": {}
        },
        {
            "label": "3-3",
            "points": [
                [
                    3124.8275862068967,
                    1186.896551724138
                ]
            ],
            "group_id": 69,
            "shape_type": "point",
            "flags": {}
        },
        {
            "label": "3-1",
            "points": [
                [
                    3188.0239520958085,
                    1164.6706586826347
                ]
            ],
            "group_id": 70,
            "shape_type": "point",
            "flags": {}
        },
        {
            "label": "3-2",
            "points": [
                [
                    3184.431137724551,
                    1202.3952095808384
                ]
            ],
            "group_id": 70,
            "shape_type": "point",
            "flags": {}
        },
        {
            "label": "3-3",
            "points": [
                [
                    3179.6407185628746,
                    1232.934131736527
                ]
            ],
            "group_id": 70,
            "shape_type": "point",
            "flags": {}
        },
        {
            "label": "3-1",
            "points": [
                [
                    3213.173652694611,
                    1177.245508982036
                ]
            ],
            "group_id": 71,
            "shape_type": "point",
            "flags": {}
        },
        {
            "label": "3-2",
            "points": [
                [
                    3227.5449101796407,
                    1206.5868263473055
                ]
            ],
            "group_id": 71,
            "shape_type": "point",
            "flags": {}
        },
        {
            "label": "3-3",
            "points": [
                [
                    3244.9101796407185,
                    1233.5329341317365
                ]
            ],
            "group_id": 71,
            "shape_type": "point",
            "flags": {}
        },
        {
            "label": "3-1",
            "points": [
                [
                    3197.604790419162,
                    1203.5928143712576
                ]
            ],
            "group_id": 72,
            "shape_type": "point",
            "flags": {}
        },
        {
            "label": "3-2",
            "points": [
                [
                    3197.604790419162,
                    1230.5389221556886
                ]
            ],
            "group_id": 72,
            "shape_type": "point",
            "flags": {}
        },
        {
            "label": "3-3",
            "points": [
                [
                    3189.820359281437,
                    1265.868263473054
                ]
            ],
            "group_id": 72,
            "shape_type": "point",
            "flags": {}
        },
        {
            "label": "2-1",
            "points": [
                [
                    3203.5928143712576,
                    1205.9880239520958
                ]
            ],
            "group_id": 73,
            "shape_type": "point",
            "flags": {}
        },
        {
            "label": "2-2",
            "points": [
                [
                    3217.964071856288,
                    1228.1437125748503
                ]
            ],
            "group_id": 73,
            "shape_type": "point",
            "flags": {}
        },
        {
            "label": "4-1",
            "points": [
                [
                    3183.8323353293413,
                    1338.9221556886228
                ]
            ],
            "group_id": 74,
            "shape_type": "point",
            "flags": {}
        },
        {
            "label": "4-2",
            "points": [
                [
                    3202.3952095808386,
                    1343.11377245509
                ]
            ],
            "group_id": 74,
            "shape_type": "point",
            "flags": {}
        },
        {
            "label": "4-3",
            "points": [
                [
                    3223.9520958083835,
                    1329.3413173652696
                ]
            ],
            "group_id": 74,
            "shape_type": "point",
            "flags": {}
        },
        {
            "label": "4-4",
            "points": [
                [
                    3239.5209580838323,
                    1302.3952095808384
                ]
            ],
            "group_id": 74,
            "shape_type": "point",
            "flags": {}
        },
        {
            "label": "3-1",
            "points": [
                [
                    3182.634730538922,
                    1382.6347305389222
                ]
            ],
            "group_id": 75,
            "shape_type": "point",
            "flags": {}
        },
        {
            "label": "3-2",
            "points": [
                [
                    3194.6107784431138,
                    1417.365269461078
                ]
            ],
            "group_id": 75,
            "shape_type": "point",
            "flags": {}
        },
        {
            "label": "3-3",
            "points": [
                [
                    3212.5748502994015,
                    1447.9041916167666
                ]
            ],
            "group_id": 75,
            "shape_type": "point",
            "flags": {}
        },
        {
            "label": "3-1",
            "points": [
                [
                    3146.107784431138,
                    1386.2275449101796
                ]
            ],
            "group_id": 76,
            "shape_type": "point",
            "flags": {}
        },
        {
            "label": "3-2",
            "points": [
                [
                    3172.4550898203593,
                    1425.1497005988024
                ]
            ],
            "group_id": 76,
            "shape_type": "point",
            "flags": {}
        },
        {
            "label": "3-3",
            "points": [
                [
                    3186.8263473053894,
                    1448.5029940119762
                ]
            ],
            "group_id": 76,
            "shape_type": "point",
            "flags": {}
        },
        {
            "label": "2-1",
            "points": [
                [
                    3098.802395209581,
                    1292.8143712574852
                ]
            ],
            "group_id": 77,
            "shape_type": "point",
            "flags": {}
        },
        {
            "label": "2-2",
            "points": [
                [
                    3076.047904191617,
                    1285.0299401197606
                ]
            ],
            "group_id": 77,
            "shape_type": "point",
            "flags": {}
        },
        {
            "label": "3-1",
            "points": [
                [
                    3108.982035928144,
                    1394.6107784431138
                ]
            ],
            "group_id": 78,
            "shape_type": "point",
            "flags": {}
        },
        {
            "label": "3-2",
            "points": [
                [
                    3100.5988023952095,
                    1426.3473053892217
                ]
            ],
            "group_id": 78,
            "shape_type": "point",
            "flags": {}
        },
        {
            "label": "3-3",
            "points": [
                [
                    3082.0359281437127,
                    1447.9041916167666
                ]
            ],
            "group_id": 78,
            "shape_type": "point",
            "flags": {}
        },
        {
            "label": "3-1",
            "points": [
                [
                    3099.4011976047905,
                    1379.6407185628743
                ]
            ],
            "group_id": 79,
            "shape_type": "point",
            "flags": {}
        },
        {
            "label": "3-2",
            "points": [
                [
                    3095.2095808383233,
                    1411.9760479041918
                ]
            ],
            "group_id": 79,
            "shape_type": "point",
            "flags": {}
        },
        {
            "label": "3-3",
            "points": [
                [
                    3119.7604790419164,
                    1462.874251497006
                ]
            ],
            "group_id": 79,
            "shape_type": "point",
            "flags": {}
        },
        {
            "label": "3-1",
            "points": [
                [
                    3068.2634730538925,
                    1584.431137724551
                ]
            ],
            "group_id": 80,
            "shape_type": "point",
            "flags": {}
        },
        {
            "label": "3-2",
            "points": [
                [
                    3068.862275449102,
                    1553.2934131736527
                ]
            ],
            "group_id": 80,
            "shape_type": "point",
            "flags": {}
        },
        {
            "label": "3-3",
            "points": [
                [
                    3073.652694610779,
                    1519.7604790419161
                ]
            ],
            "group_id": 80,
            "shape_type": "point",
            "flags": {}
        },
        {
            "label": "3-1",
            "points": [
                [
                    3175.4491017964074,
                    1560.4790419161677
                ]
            ],
            "group_id": 81,
            "shape_type": "point",
            "flags": {}
        },
        {
            "label": "3-2",
            "points": [
                [
                    3186.8263473053894,
                    1597.6047904191616
                ]
            ],
            "group_id": 81,
            "shape_type": "point",
            "flags": {}
        },
        {
            "label": "3-3",
            "points": [
                [
                    3191.0179640718566,
                    1629.3413173652696
                ]
            ],
            "group_id": 81,
            "shape_type": "point",
            "flags": {}
        },
        {
            "label": "2-1",
            "points": [
                [
                    3156.8862275449105,
                    1577.8443113772455
                ]
            ],
            "group_id": 82,
            "shape_type": "point",
            "flags": {}
        },
        {
            "label": "2-2",
            "points": [
                [
                    3204.7904191616767,
                    1594.6107784431138
                ]
            ],
            "group_id": 82,
            "shape_type": "point",
            "flags": {}
        },
        {
            "label": "3-1",
            "points": [
                [
                    3098.802395209581,
                    1607.7844311377246
                ]
            ],
            "group_id": 83,
            "shape_type": "point",
            "flags": {}
        },
        {
            "label": "3-2",
            "points": [
                [
                    3107.784431137725,
                    1616.1676646706587
                ]
            ],
            "group_id": 83,
            "shape_type": "point",
            "flags": {}
        },
        {
            "label": "3-3",
            "points": [
                [
                    3114.37125748503,
                    1624.5508982035929
                ]
            ],
            "group_id": 83,
            "shape_type": "point",
            "flags": {}
        },
        {
            "label": "3-1",
            "points": [
                [
                    3084.431137724551,
                    1583.8323353293413
                ]
            ],
            "group_id": 84,
            "shape_type": "point",
            "flags": {}
        },
        {
            "label": "3-2",
            "points": [
                [
                    3085.6287425149703,
                    1557.4850299401198
                ]
            ],
            "group_id": 84,
            "shape_type": "point",
            "flags": {}
        },
        {
            "label": "3-3",
            "points": [
                [
                    3091.616766467066,
                    1527.5449101796407
                ]
            ],
            "group_id": 84,
            "shape_type": "point",
            "flags": {}
        },
        {
            "label": "3-1",
            "points": [
                [
                    3158.682634730539,
                    1720.359281437126
                ]
            ],
            "group_id": 85,
            "shape_type": "point",
            "flags": {}
        },
        {
            "label": "3-2",
            "points": [
                [
                    3178.443113772455,
                    1740.7185628742516
                ]
            ],
            "group_id": 85,
            "shape_type": "point",
            "flags": {}
        },
        {
            "label": "3-3",
            "points": [
                [
                    3200.5988023952095,
                    1750.2994011976048
                ]
            ],
            "group_id": 85,
            "shape_type": "point",
            "flags": {}
        },
        {
            "label": "3-1",
            "points": [
                [
                    3153.8922155688624,
                    1768.2634730538923
                ]
            ],
            "group_id": 86,
            "shape_type": "point",
            "flags": {}
        },
        {
            "label": "3-2",
            "points": [
                [
                    3153.293413173653,
                    1792.8143712574852
                ]
            ],
            "group_id": 86,
            "shape_type": "point",
            "flags": {}
        },
        {
            "label": "3-3",
            "points": [
                [
                    3143.11377245509,
                    1817.365269461078
                ]
            ],
            "group_id": 86,
            "shape_type": "point",
            "flags": {}
        },
        {
            "label": "1-1",
            "points": [
                [
                    3181.437125748503,
                    1808.982035928144
                ]
            ],
            "group_id": 87,
            "shape_type": "point",
            "flags": {}
        },
        {
            "label": "4-1",
            "points": [
                [
                    3164.0718562874254,
                    1751.497005988024
                ]
            ],
            "group_id": 88,
            "shape_type": "point",
            "flags": {}
        },
        {
            "label": "4-2",
            "points": [
                [
                    3168.2634730538925,
                    1780.2395209580839
                ]
            ],
            "group_id": 88,
            "shape_type": "point",
            "flags": {}
        },
        {
            "label": "4-3",
            "points": [
                [
                    3158.682634730539,
                    1819.1616766467066
                ]
            ],
            "group_id": 88,
            "shape_type": "point",
            "flags": {}
        },
        {
            "label": "4-4",
            "points": [
                [
                    3147.9041916167666,
                    1834.7305389221558
                ]
            ],
            "group_id": 88,
            "shape_type": "point",
            "flags": {}
        },
        {
            "label": "3-1",
            "points": [
                [
                    3040.1197604790423,
                    1994.6107784431138
                ]
            ],
            "group_id": 89,
            "shape_type": "point",
            "flags": {}
        },
        {
            "label": "3-2",
            "points": [
                [
                    3034.131736526946,
                    2024.5508982035929
                ]
            ],
            "group_id": 89,
            "shape_type": "point",
            "flags": {}
        },
        {
            "label": "3-3",
            "points": [
                [
                    3027.5449101796407,
                    2053.8922155688624
                ]
            ],
            "group_id": 89,
            "shape_type": "point",
            "flags": {}
        },
        {
            "label": "3-1",
            "points": [
                [
                    3082.634730538922,
                    1920.359281437126
                ]
            ],
            "group_id": 90,
            "shape_type": "point",
            "flags": {}
        },
        {
            "label": "3-2",
            "points": [
                [
                    3111.9760479041915,
                    1920.9580838323354
                ]
            ],
            "group_id": 90,
            "shape_type": "point",
            "flags": {}
        },
        {
            "label": "3-3",
            "points": [
                [
                    3143.7125748502995,
                    1920.359281437126
                ]
            ],
            "group_id": 90,
            "shape_type": "point",
            "flags": {}
        },
        {
            "label": "2-1",
            "points": [
                [
                    3128.74251497006,
                    1946.1077844311378
                ]
            ],
            "group_id": 91,
            "shape_type": "point",
            "flags": {}
        },
        {
            "label": "2-2",
            "points": [
                [
                    3159.2814371257487,
                    1961.0778443113772
                ]
            ],
            "group_id": 91,
            "shape_type": "point",
            "flags": {}
        },
        {
            "label": "4-1",
            "points": [
                [
                    3086.8263473053894,
                    1949.7005988023952
                ]
            ],
            "group_id": 92,
            "shape_type": "point",
            "flags": {}
        },
        {
            "label": "4-2",
            "points": [
                [
                    3089.820359281437,
                    1988.0239520958085
                ]
            ],
            "group_id": 92,
            "shape_type": "point",
            "flags": {}
        },
        {
            "label": "4-3",
            "points": [
                [
                    3092.2155688622756,
                    2021.556886227545
                ]
            ],
            "group_id": 92,
            "shape_type": "point",
            "flags": {}
        },
        {
            "label": "4-4",
            "points": [
                [
                    3094.011976047904,
                    2054.491017964072
                ]
            ],
            "group_id": 92,
            "shape_type": "point",
            "flags": {}
        },
        {
            "label": "3-1",
            "points": [
                [
                    3067.6646706586826,
                    2142.5149700598804
                ]
            ],
            "group_id": 93,
            "shape_type": "point",
            "flags": {}
        },
        {
            "label": "3-2",
            "points": [
                [
                    3096.407185628743,
                    2161.676646706587
                ]
            ],
            "group_id": 93,
            "shape_type": "point",
            "flags": {}
        },
        {
            "label": "3-3",
            "points": [
                [
                    3130.538922155689,
                    2170.6586826347307
                ]
            ],
            "group_id": 93,
            "shape_type": "point",
            "flags": {}
        },
        {
            "label": "3-1",
            "points": [
                [
                    3055.688622754491,
                    2176.6467065868264
                ]
            ],
            "group_id": 94,
            "shape_type": "point",
            "flags": {}
        },
        {
            "label": "3-2",
            "points": [
                [
                    3063.473053892216,
                    2204.191616766467
                ]
            ],
            "group_id": 94,
            "shape_type": "point",
            "flags": {}
        },
        {
            "label": "3-3",
            "points": [
                [
                    3070.6586826347307,
                    2232.934131736527
                ]
            ],
            "group_id": 94,
            "shape_type": "point",
            "flags": {}
        },
        {
            "label": "3-1",
            "points": [
                [
                    3030.538922155689,
                    2171.8562874251497
                ]
            ],
            "group_id": 95,
            "shape_type": "point",
            "flags": {}
        },
        {
            "label": "3-2",
            "points": [
                [
                    3020.359281437126,
                    2209.5808383233534
                ]
            ],
            "group_id": 95,
            "shape_type": "point",
            "flags": {}
        },
        {
            "label": "3-3",
            "points": [
                [
                    3003.5928143712576,
                    2238.9221556886228
                ]
            ],
            "group_id": 95,
            "shape_type": "point",
            "flags": {}
        },
        {
            "label": "3-1",
            "points": [
                [
                    3212.5748502994015,
                    2054.491017964072
                ]
            ],
            "group_id": 96,
            "shape_type": "point",
            "flags": {}
        },
        {
            "label": "3-2",
            "points": [
                [
                    3182.634730538922,
                    2071.25748502994
                ]
            ],
            "group_id": 96,
            "shape_type": "point",
            "flags": {}
        },
        {
            "label": "3-3",
            "points": [
                [
                    3150.2994011976048,
                    2074.2514970059883
                ]
            ],
            "group_id": 96,
            "shape_type": "point",
            "flags": {}
        },
        {
            "label": "3-1",
            "points": [
                [
                    3208.982035928144,
                    2083.2335329341317
                ]
            ],
            "group_id": 97,
            "shape_type": "point",
            "flags": {}
        },
        {
            "label": "3-2",
            "points": [
                [
                    3176.6467065868264,
                    2094.6107784431138
                ]
            ],
            "group_id": 97,
            "shape_type": "point",
            "flags": {}
        },
        {
            "label": "3-3",
            "points": [
                [
                    3146.7065868263476,
                    2095.808383233533
                ]
            ],
            "group_id": 97,
            "shape_type": "point",
            "flags": {}
        },
        {
            "label": "3-1",
            "points": [
                [
                    3206.5868263473053,
                    2108.3832335329344
                ]
            ],
            "group_id": 98,
            "shape_type": "point",
            "flags": {}
        },
        {
            "label": "3-2",
            "points": [
                [
                    3183.8323353293413,
                    2133.5329341317365
                ]
            ],
            "group_id": 98,
            "shape_type": "point",
            "flags": {}
        },
        {
            "label": "3-3",
            "points": [
                [
                    3162.2754491017968,
                    2147.9041916167666
                ]
            ],
            "group_id": 98,
            "shape_type": "point",
            "flags": {}
        },
        {
            "label": "2-1",
            "points": [
                [
                    3242.5149700598804,
                    2126.3473053892217
                ]
            ],
            "group_id": 99,
            "shape_type": "point",
            "flags": {}
        },
        {
            "label": "2-2",
            "points": [
                [
                    3236.5269461077846,
                    2158.682634730539
                ]
            ],
            "group_id": 99,
            "shape_type": "point",
            "flags": {}
        },
        {
            "label": "2-1",
            "points": [
                [
                    3223.353293413174,
                    2158.0838323353296
                ]
            ],
            "group_id": 100,
            "shape_type": "point",
            "flags": {}
        },
        {
            "label": "2-2",
            "points": [
                [
                    3213.7724550898206,
                    2187.425149700599
                ]
            ],
            "group_id": 100,
            "shape_type": "point",
            "flags": {}
        },
        {
            "label": "3-1",
            "points": [
                [
                    3102.994011976048,
                    2091.616766467066
                ]
            ],
            "group_id": 101,
            "shape_type": "point",
            "flags": {}
        },
        {
            "label": "3-2",
            "points": [
                [
                    3091.616766467066,
                    2135.928143712575
                ]
            ],
            "group_id": 101,
            "shape_type": "point",
            "flags": {}
        },
        {
            "label": "3-3",
            "points": [
                [
                    3079.041916167665,
                    2174.2514970059883
                ]
            ],
            "group_id": 101,
            "shape_type": "point",
            "flags": {}
        },
        {
            "label": "2-1",
            "points": [
                [
                    2966.4670658682635,
                    2371.8562874251497
                ]
            ],
            "group_id": 102,
            "shape_type": "point",
            "flags": {}
        },
        {
            "label": "2-2",
            "points": [
                [
                    2929.9401197604793,
                    2386.22754491018
                ]
            ],
            "group_id": 102,
            "shape_type": "point",
            "flags": {}
        },
        {
            "label": "3-1",
            "points": [
                [
                    2992.2155688622756,
                    2392.814371257485
                ]
            ],
            "group_id": 103,
            "shape_type": "point",
            "flags": {}
        },
        {
            "label": "3-2",
            "points": [
                [
                    3008.3832335329344,
                    2426.946107784431
                ]
            ],
            "group_id": 103,
            "shape_type": "point",
            "flags": {}
        },
        {
            "label": "3-3",
            "points": [
                [
                    3034.730538922156,
                    2452.6946107784433
                ]
            ],
            "group_id": 103,
            "shape_type": "point",
            "flags": {}
        },
        {
            "label": "3-1",
            "points": [
                [
                    3114.9700598802397,
                    2487.425149700599
                ]
            ],
            "group_id": 104,
            "shape_type": "point",
            "flags": {}
        },
        {
            "label": "3-2",
            "points": [
                [
                    3085.029940119761,
                    2495.808383233533
                ]
            ],
            "group_id": 104,
            "shape_type": "point",
            "flags": {}
        },
        {
            "label": "3-3",
            "points": [
                [
                    3058.682634730539,
                    2486.8263473053894
                ]
            ],
            "group_id": 104,
            "shape_type": "point",
            "flags": {}
        },
        {
            "label": "3-1",
            "points": [
                [
                    2988.622754491018,
                    2453.293413173653
                ]
            ],
            "group_id": 105,
            "shape_type": "point",
            "flags": {}
        },
        {
            "label": "3-2",
            "points": [
                [
                    2971.25748502994,
                    2465.2694610778444
                ]
            ],
            "group_id": 105,
            "shape_type": "point",
            "flags": {}
        },
        {
            "label": "3-3",
            "points": [
                [
                    2934.730538922156,
                    2474.850299401198
                ]
            ],
            "group_id": 105,
            "shape_type": "point",
            "flags": {}
        },
        {
            "label": "1-1",
            "points": [
                [
                    2968.2634730538925,
                    2626.946107784431
                ]
            ],
            "group_id": 106,
            "shape_type": "point",
            "flags": {}
        },
        {
            "label": "1-1",
            "points": [
                [
                    3032.3353293413174,
                    2713.173652694611
                ]
            ],
            "group_id": 107,
            "shape_type": "point",
            "flags": {}
        },
        {
            "label": "2-1",
            "points": [
                [
                    2953.293413173653,
                    2701.197604790419
                ]
            ],
            "group_id": 108,
            "shape_type": "point",
            "flags": {}
        },
        {
            "label": "2-2",
            "points": [
                [
                    2957.48502994012,
                    2711.9760479041915
                ]
            ],
            "group_id": 108,
            "shape_type": "point",
            "flags": {}
        }
    ],
    "imageData": null
}